2005/CS.v
`timescale 1ns/10ps
/*
 * IC Contest Computational System (CS)
*/
module CS(Y, X, reset, clk);

input clk, reset; 
input [7:0] X;
output reg [9:0] Y;//remember to set reg

reg [7:0] Xavg;
reg [11:0] Xapp;
reg [7:0] X_series [8:0];//save 9 numbers
reg [3:0] i;//to count 9
reg [10:0] sum;//the sum of 9 number

always@(posedge clk or posedge reset)begin
  if(reset) begin
    for(i=0;i<9;i=i+1)
      X_series[i] <= 0; 
      i <= 0;
      sum <= 0;
  end
  else begin 
    for(i=0;i<8;i=i+1)
      X_series[i] <= X_series[i+1] ;
      /*  X_series[0]=X_series[1];
          X_series[1]=X_series[2];
          X_series[2]=X_series[3];
          X_series[3]=X_series[4];
          X_series[4]=X_series[5];
          X_series[5]=X_series[6];
          X_series[6]=X_series[7];
          X_series[7]=X_series[8];
      */
    X_series[8] <= X;//use new number to replace 
    sum <= sum+X-X_series[0];//delete X_series[0] and add new X
  end
end 


always @(*)begin
  Xapp=0;//remember to initialize 
  
  for(i=0;i<9;i=i+1)begin
    
    if((X_series[i]<=sum/9) && (X_series[i] > Xapp))//find the number which is biggest number of 9 numbers and smaller than average 
      Xapp=X_series[i];
  end
  Y=(sum+(Xapp<<3)+Xapp)>>3;//the devidor is 9-1=8//use shift is fast
end

endmodule

2005/testfixture.v
`timescale 1ns/10ps
`define CYCLE  10        	// Modify your clock period here
`define SDFFILE "cs_syn.sdf"	// Modify your sdf file name
`define INFILE "in.dat"
`define OUTFILE "out_golden.dat"  

module test;
parameter INPUT_DATA = `INFILE;
parameter GOLDEN = `OUTFILE;
parameter N_PAT = 2000;
parameter t_reset = `CYCLE*2;

reg reset;
reg clk;
reg ready;
reg stop;
reg flag1, flag2;
wire pclk = clk ;

integer i, out_f, err, pattern_num;
integer a, b;
reg     [7:0] X;
reg 	[7:0] data_base1 [0:20000];
reg	[9:0] data_base2 [0:20000];
reg 	[9:0] data_tmp;
wire    [9:0] Y; 

CS top (.Y(Y), .X(X), .reset(reset), .clk(clk)); 

//initial $sdf_annotate(`SDFFILE, top);

initial	$readmemh (INPUT_DATA, data_base1);

initial $readmemh (GOLDEN, data_base2);

initial begin
   reset = 1'b0;
   clk = 1'b1;
   stop = 1'b0;
   err = 0;
   a = 0;
   b = 0;
   pattern_num = 0 ;     
end

initial begin
$dumpfile("cs.vcd");
$dumpvars;
//$fsdbDumpfile("cs.fsdb");
//$fsdbDumpvars; 

   out_f = $fopen("out.dat");
   if (out_f == 0) begin
        $display("Output file open error !");
        $finish;
   end
end

always begin #(`CYCLE/2) clk = ~clk;
end


specify
$setup(Y, posedge pclk, 0.5, flag1);
$hold(posedge pclk, Y, 0.5, flag2); 
endspecify 

always @(flag1)
   if(flag1 == 1'b1 || flag1 == 1'b0)
     a = a +1;

always @(flag2)
   if(flag2 == 1'b1  || flag2 == 1'b0)
     b = b +1;


initial 
  begin
    X = data_base1[0] ;
    @(negedge clk) reset = 1'b1;
    #t_reset reset = 1'b0;  ready = 1'b0;
    #`CYCLE
    for (i = 1; i < N_PAT; i = i + 1) 
    begin
      @(negedge clk) X = data_base1[i]; 
      if (i==8)
        @(posedge clk) ready = 1'b1;                      
    end 
  end  
 		
always @(posedge clk) 
  begin
   if (pattern_num + 9 > N_PAT)      stop = 1 ;
   else if (ready) 
     begin
       data_tmp = data_base2[pattern_num]; 
       $fdisplay(out_f,"%h", Y); 
         if (Y !== data_tmp) 
           begin
             $display("ERROR at %d:output %h !=expect %h ",pattern_num, Y, data_tmp);
             err = err + 1 ;
           end
       pattern_num = pattern_num + 1 ; 
     end

  end  

initial begin
      @(posedge stop)
      $display("---------------------------------------------\n");
      if (a !=0)
         $display("There are %d setup time violations by Y\n", a);
      if (b !=0)
         $display("There are %d hold time violations by Y\n", b);
      $display("---------------------------------------------\n");
      if (err == 0)
        begin
          $display("All data have been generated successfully!\n");
          $display("-------------------PASS-------------------\n");
        end
      else 
         $display("There are %d errors!\n", err);
      $display("---------------------------------------------\n");
      $finish;
   end
endmodule

2005/cs.vcd
$date
	Fri Jan 21 00:48:28 2022
$end
$version
	ModelSim Version 10.1c
$end
$timescale
	10ps
$end
$scope module test $end
$var parameter 48 ! INPUT_DATA $end
$var parameter 112 " GOLDEN $end
$var parameter 32 # N_PAT $end
$var parameter 32 $ t_reset $end
$var reg 1 % reset $end
$var reg 1 & clk $end
$var reg 1 ' ready $end
$var reg 1 ( stop $end
$var reg 1 ) flag1 $end
$var reg 1 * flag2 $end
$var wire 1 + pclk $end
$var integer 32 , i $end
$var integer 32 - out_f $end
$var integer 32 . err $end
$var integer 32 / pattern_num $end
$var integer 32 0 a $end
$var integer 32 1 b $end
$var reg 8 2 X [7:0] $end
$var reg 10 3 data_tmp [9:0] $end
$var wire 1 4 Y [9] $end
$var wire 1 5 Y [8] $end
$var wire 1 6 Y [7] $end
$var wire 1 7 Y [6] $end
$var wire 1 8 Y [5] $end
$var wire 1 9 Y [4] $end
$var wire 1 : Y [3] $end
$var wire 1 ; Y [2] $end
$var wire 1 < Y [1] $end
$var wire 1 = Y [0] $end
$scope module top $end
$var wire 1 > clk $end
$var wire 1 ? reset $end
$var wire 1 @ X [7] $end
$var wire 1 A X [6] $end
$var wire 1 B X [5] $end
$var wire 1 C X [4] $end
$var wire 1 D X [3] $end
$var wire 1 E X [2] $end
$var wire 1 F X [1] $end
$var wire 1 G X [0] $end
$var reg 10 H Y [9:0] $end
$var reg 8 I Xavg [7:0] $end
$var reg 12 J Xapp [11:0] $end
$var reg 4 K i [3:0] $end
$var reg 11 L sum [10:0] $end
$upscope $end
$upscope $end
$enddefinitions $end
#0
$dumpvars
0%
1&
x'
0(
x)
x*
b10001111 2
bx 3
b0xxxxxxxxx H
bx I
b0 J
b1001 K
bx L
b11111010000 #
b10100 $
b11010010110111000101110011001000110000101110100 !
b110111101110101011101000101111101100111011011110110110001100100011001010110111000101110011001000110000101110100 "
bx ,
b10 -
b0 .
b0 /
b0 0
b0 1
1+
x=
x<
x;
x:
x9
x8
x7
x6
x5
04
1>
0?
1G
1F
1E
1D
0C
0B
0A
1@
$end
#500
0&
0+
0>
1%
1?
b0 K
b1 K
b10 K
b11 K
b100 K
b101 K
b110 K
b111 K
b1000 K
b1001 K
b0 K
b0 L
b1 K
b10 K
b11 K
b100 K
b101 K
b110 K
b111 K
b1000 K
b1001 K
b0 H
0=
0<
0;
0:
09
08
07
06
05
#1000
1&
1+
1>
b0 K
b1 K
b10 K
b11 K
b100 K
b101 K
b110 K
b111 K
b1000 K
b1001 K
b0 K
#1500
0&
0+
0>
#2000
1&
1+
1>
b1 K
b10 K
b11 K
b100 K
b101 K
b110 K
b111 K
b1000 K
b1001 K
b0 K
#2500
0%
0'
0&
0+
0?
0>
#3000
1&
1+
1>
b1 K
b10 K
b11 K
b100 K
b101 K
b110 K
b111 K
b1000 K
b10001111 L
b0 K
b1 K
b10 K
b11 K
b100 K
b101 K
b110 K
b111 K
b1000 K
b1001 K
b10001 H
1=
19
0*
b1 1
#3500
b1 ,
0&
0+
0>
b1011 2
b10 ,
0E
0@
#4000
1&
1+
1>
b0 K
b1 K
b10 K
b11 K
b100 K
b101 K
b110 K
b111 K
b1000 K
b10011010 L
b0 K
b1 K
b10 K
b11 K
b100 K
b101 K
b110 K
b111 K
b1000 K
b1011 J
b1001 K
b11111 H
1<
1;
1:
1*
b10 1
#4500
0&
0+
0>
b1011101 2
b11 ,
0F
1E
1C
1A
#5000
1&
1+
1>
b0 K
b1 K
b10 K
b11 K
b100 K
b101 K
b110 K
b111 K
b1000 K
b11110111 L
b0 J
b0 K
b1 K
b10 K
b11 K
b100 K
b101 K
b110 K
b111 K
b1011 J
b1000 K
b1001 K
b101011 H
0;
09
18
0*
b11 1
#5500
0&
0+
0>
b100000 2
b100 ,
0G
0E
0D
0C
1B
0A
#6000
1&
1+
1>
b0 K
b1 K
b10 K
b11 K
b100 K
b101 K
b110 K
b111 K
b1000 K
b100010111 L
b0 J
b0 K
b1 K
b10 K
b11 K
b100 K
b101 K
b110 K
b1011 J
b111 K
b1000 K
b1001 K
b101111 H
1;
1*
b100 1
#6500
0&
0+
0>
b11110011 2
b101 ,
1G
1F
1C
1A
1@
#7000
1&
1+
1>
b0 K
b1 K
b10 K
b11 K
b100 K
b101 K
b110 K
b111 K
b1000 K
b1000001010 L
b0 J
b0 K
b1 K
b10 K
b11 K
b100 K
b101 K
b1011 J
b110 K
b111 K
b100000 J
b1000 K
b1001 K
b1100101 H
0<
0:
17
0*
b101 1
#7500
0&
0+
0>
b111110 2
b110 ,
0G
1E
1D
0A
0@
#8000
1&
1+
1>
b0 K
b1 K
b10 K
b11 K
b100 K
b101 K
b110 K
b111 K
b1000 K
b1001001000 L
b0 J
b0 K
b1 K
b10 K
b11 K
b100 K
b1011 J
b101 K
b110 K
b100000 J
b111 K
b1000 K
b111110 J
b1001 K
b10001110 H
0=
1<
1:
08
07
16
1*
b110 1
#8500
0&
0+
0>
b11100101 2
b111 ,
1G
0F
0D
0C
1A
1@
#9000
1&
1+
1>
b0 K
b1 K
b10 K
b11 K
b100 K
b101 K
b110 K
b111 K
b1000 K
b1100101101 L
b0 J
b0 K
b1 K
b10 K
b11 K
b1011 J
b100 K
b101 K
b100000 J
b110 K
b111 K
b111110 J
b1000 K
b1001 K
b10101011 H
1=
0;
18
0*
b111 1
#9500
0&
0+
0>
b11 2
b1000 ,
1F
0E
0B
0A
0@
#10000
1&
1+
1>
b0 K
b1 K
b10 K
b11 K
b100 K
b101 K
b110 K
b111 K
b1000 K
b1100110000 L
b0 J
b0 K
b1 K
b10 K
b1011 J
b11 K
b100 K
b100000 J
b101 K
b110 K
b111110 J
b111 K
b1000 K
b1001 K
#10500
0&
0+
0>
b1100 2
0G
0F
1E
1D
#11000
1&
1+
1>
b0 K
b1 K
b10 K
b11 K
b100 K
b101 K
b110 K
b111 K
b1000 K
1'
b1001 ,
b1100111100 L
b0 J
b0 K
b1 K
b1011 J
b10 K
b11 K
b100000 J
b100 K
b101 K
b111110 J
b110 K
b111 K
b1000 K
b1001 K
b10101101 H
0<
1;
1*
b1000 1
#11500
0&
0+
0>
b1110100 2
b1010 ,
0D
1C
1B
1A
#12000
1&
1+
1>
b0 K
b1 K
b10 K
b11 K
b100 K
b101 K
b110 K
b111 K
b1000 K
b10101101 3
b1 /
b1100100001 L
b0 J
b0 K
b1011 J
b1 K
b10 K
b100000 J
b11 K
b100 K
b111110 J
b101 K
b110 K
b111 K
b1000 K
b1001 K
b10101001 H
0;
0*
b1001 1
#12500
0&
0+
0>
b1111001 2
b1011 ,
1G
0E
1D
#13000
1&
1+
1>
b0 K
b1 K
b10 K
b11 K
b100 K
b101 K
b110 K
b111 K
b1000 K
b10101001 3
b10 /
b1110001111 L
b0 J
b0 K
b1011101 J
b1 K
b10 K
b11 K
b100 K
b101 K
b110 K
b111 K
b1000 K
b1001 K
b11011010 H
0=
1<
19
08
17
1*
b1010 1
#13500
0&
0+
0>
b1 2
b1100 ,
0D
0C
0B
0A
#14000
1&
1+
1>
b0 K
b1 K
b10 K
b11 K
b100 K
b101 K
b110 K
b111 K
b1000 K
b11011010 3
b11 /
b1100110011 L
b0 J
b0 K
b100000 J
b1 K
b10 K
b111110 J
b11 K
b100 K
b101 K
b110 K
b111 K
b1000 K
b1001 K
b10101100 H
0<
1;
09
18
07
0*
b1011 1
#14500
0&
0+
0>
b110000 2
b1101 ,
0G
1C
1B
#15000
1&
1+
1>
b0 K
b1 K
b10 K
b11 K
b100 K
b101 K
b110 K
b111 K
b1000 K
b10101100 3
b100 /
b1101000011 L
b0 J
b0 K
b1 K
b111110 J
b10 K
b11 K
b100 K
b101 K
b110 K
b111 K
b1000 K
b1001 K
b10101110 H
1<
1*
b1100 1
#15500
0&
0+
0>
b101110 2
b1110 ,
1F
1E
1D
0C
#16000
1&
1+
1>
b0 K
b1 K
b10 K
b11 K
b100 K
b101 K
b110 K
b111 K
b1000 K
b10101110 3
b101 /
b1001111110 L
b0 J
b0 K
b111110 J
b1 K
b10 K
b11 K
b100 K
b101 K
b110 K
b111 K
b1000 K
b1001 K
b10010101 H
1=
0<
0:
19
08
0*
b1101 1
#16500
0&
0+
0>
b10100100 2
b1111 ,
0F
0D
1@
#17000
1&
1+
1>
b0 K
b1 K
b10 K
b11 K
b100 K
b101 K
b110 K
b111 K
b1000 K
b10010101 3
b110 /
b1011100100 L
b0 J
b0 K
b1 K
b11 J
b10 K
b1100 J
b11 K
b100 K
b101 K
b110 K
b110000 J
b111 K
b1000 K
b1001 K
b10010010 H
0=
1<
0;
1*
b1110 1
#17500
0&
0+
0>
b1110110 2
b10000 ,
1F
1C
1A
0@
#18000
1&
1+
1>
b0 K
b1 K
b10 K
b11 K
b100 K
b101 K
b110 K
b111 K
b1000 K
b10010010 3
b111 /
b1001110101 L
b0 J
b0 K
b11 J
b1 K
b1100 J
b10 K
b11 K
b100 K
b101 K
b110000 J
b110 K
b111 K
b1000 K
b1001 K
b10000100 H
0<
1;
09
0*
b1111 1
#18500
0&
0+
0>
b10000100 2
b10001 ,
0F
0C
0B
0A
1@
#19000
1&
1+
1>
b0 K
b1 K
b10 K
b11 K
b100 K
b101 K
b110 K
b111 K
b1000 K
b10000100 3
b1000 /
b1011110110 L
b0 J
b0 K
b1100 J
b1 K
b10 K
b11 K
b100 K
b110000 J
b101 K
b110 K
b111 K
b1000 K
b1001 K
b10010100 H
19
1*
b10000 1
#19500
0&
0+
0>
b1010001 2
b10010 ,
1G
0E
1C
1A
0@
#20000
1&
1+
1>
b0 K
b1 K
b10 K
b11 K
b100 K
b101 K
b110 K
b111 K
b1000 K
b10010100 3
b1001 /
b1100111011 L
b0 J
b0 K
b1 K
b10 K
b1 J
b11 K
b110000 J
b100 K
b101 K
b110 K
b111 K
b1000 K
b1010001 J
b1001 K
b11000010 H
1<
0;
09
17
0*
b10001 1
#20500
0&
0+
0>
b11010110 2
b10011 ,
0G
1F
1E
1@
#21000
1&
1+
1>
b0 K
b1 K
b10 K
b11 K
b100 K
b101 K
b110 K
b111 K
b1000 K
b11000010 3
b1010 /
b1110011101 L
b0 J
b0 K
b1 K
b1 J
b10 K
b110000 J
b11 K
b100 K
b101 K
b110 K
b111 K
b1010001 J
b1000 K
b1001 K
b11001110 H
1;
1:
1*
b10010 1
#21500
0&
0+
0>
b1110000 2
b10100 ,
0F
0E
1B
0@
#22000
1&
1+
1>
b0 K
b1 K
b10 K
b11 K
b100 K
b101 K
b110 K
b111 K
b1000 K
b11001110 3
b1011 /
b1110010100 L
b0 J
b0 K
b1 J
b1 K
b110000 J
b10 K
b11 K
b100 K
b101 K
b110 K
b1010001 J
b111 K
b1000 K
b1001 K
b11001101 H
1=
0<
0*
b10011 1
#22500
0&
0+
0>
b110101 2
b10101 ,
1G
1E
0A
#23000
1&
1+
1>
b0 K
b1 K
b10 K
b11 K
b100 K
b101 K
b110 K
b111 K
b1000 K
b11001101 3
b1100 /
b1111001000 L
b0 J
b0 K
b110000 J
b1 K
b10 K
b11 K
b100 K
b101 K
b1010001 J
b110 K
b111 K
b1000 K
b1001 K
b11010100 H
0=
0:
19
1*
b10100 1
#23500
0&
0+
0>
b10000 2
b10110 ,
0G
0E
0B
#24000
1&
1+
1>
b0 K
b1 K
b10 K
b11 K
b100 K
b101 K
b110 K
b111 K
b1000 K
b11010100 3
b1101 /
b1110101000 L
b0 J
b0 K
b101110 J
b1 K
b10 K
b11 K
b100 K
b1010001 J
b101 K
b110 K
b111 K
b1000 K
b1001 K
b11010000 H
0;
0*
b10101 1
#24500
0&
0+
0>
b100011 2
b10111 ,
1G
1F
0C
1B
#25000
1&
1+
1>
b0 K
b1 K
b10 K
b11 K
b100 K
b101 K
b110 K
b111 K
b1000 K
b11010000 3
b1110 /
b1110011101 L
b0 J
b0 K
b1 K
b10 K
b11 K
b1010001 J
b100 K
b101 K
b110 K
b111 K
b1000 K
b1001 K
b11001110 H
1<
1;
1:
09
1*
b10110 1
#25500
0&
0+
0>
b11100111 2
b11000 ,
1E
1A
1@
#26000
1&
1+
1>
b0 K
b1 K
b10 K
b11 K
b100 K
b101 K
b110 K
b111 K
b1000 K
b11001110 3
b1111 /
b1111100000 L
b0 J
b0 K
b1 K
b10 K
b1010001 J
b11 K
b100 K
b101 K
b110 K
b111 K
b1000 K
b1001 K
b11010111 H
1=
0:
19
0*
b10111 1
#26500
0&
0+
0>
b111011 2
b11001 ,
0E
1D
1C
0A
0@
#27000
1&
1+
1>
b0 K
b1 K
b10 K
b11 K
b100 K
b101 K
b110 K
b111 K
b1000 K
b11010111 3
b10000 /
b1110100101 L
b0 J
b0 K
b1 K
b1010001 J
b10 K
b11 K
b100 K
b101 K
b110 K
b111 K
b1000 K
b1001 K
b11001111 H
1:
09
1*
b11000 1
#27500
0&
0+
0>
b1101101 2
b11010 ,
0F
1E
0C
1A
#28000
1&
1+
1>
b0 K
b1 K
b10 K
b11 K
b100 K
b101 K
b110 K
b111 K
b1000 K
b11001111 3
b10001 /
b1110001110 L
b0 J
b0 K
b1010001 J
b1 K
b10 K
b11 K
b100 K
b101 K
b110 K
b111 K
b1000 K
b1001 K
b11001100 H
0=
0<
0*
b11001 1
#28500
0&
0+
0>
b110100 2
b11011 ,
0G
0D
1C
0A
#29000
1&
1+
1>
b0 K
b1 K
b10 K
b11 K
b100 K
b101 K
b110 K
b111 K
b1000 K
b11001100 3
b10010 /
b1101110001 L
b0 J
b0 K
b1 K
b10 K
b110101 J
b11 K
b100 K
b101 K
b110 K
b111011 J
b111 K
b1000 K
b1001 K
b10110000 H
0;
0:
19
18
07
1*
b11010 1
#29500
0&
0+
0>
b1100001 2
b11100 ,
1G
0E
0C
1A
#30000
1&
1+
1>
b0 K
b1 K
b10 K
b11 K
b100 K
b101 K
b110 K
b111 K
b1000 K
b10110000 3
b10011 /
b1011111100 L
b0 J
b0 K
b1 K
b110101 J
b10 K
b11 K
b100 K
b101 K
b111011 J
b110 K
b111 K
b1000 K
b1001 K
b10100001 H
1=
09
0*
b11011 1
#30500
0&
0+
0>
b10001001 2
b11101 ,
1D
0B
0A
1@
#31000
1&
1+
1>
b0 K
b1 K
b10 K
b11 K
b100 K
b101 K
b110 K
b111 K
b1000 K
b10100001 3
b10100 /
b1100010101 L
b0 J
b0 K
b110101 J
b1 K
b10 K
b11 K
b100 K
b111011 J
b101 K
b110 K
b111 K
b1000 K
b1001 K
b10100101 H
1;
1*
b11100 1
#31500
0&
0+
0>
b10111111 2
b11110 ,
1F
1E
1C
1B
#32000
1&
1+
1>
b0 K
b1 K
b10 K
b11 K
b100 K
b101 K
b110 K
b111 K
b1000 K
b10100101 3
b10101 /
b1110011111 L
b0 J
b0 K
b10000 J
b1 K
b100011 J
b10 K
b11 K
b111011 J
b100 K
b101 K
b110 K
b1100001 J
b111 K
b1000 K
b1001 K
b11100001 H
0;
17
0*
b11101 1
#32500
0&
0+
0>
b11011100 2
b11111 ,
0G
0F
0B
1A
#33000
1&
1+
1>
b0 K
b1 K
b10 K
b11 K
b100 K
b101 K
b110 K
b111 K
b1000 K
b11100001 3
b10110 /
b10001101011 L
b0 J
b0 K
b100011 J
b1 K
b10 K
b111011 J
b11 K
b1101101 J
b100 K
b101 K
b110 K
b111 K
b1000 K
b1001 K
b100001000 H
0=
1:
08
07
06
15
1*
b11110 1
#33500
0&
0+
0>
b11010011 2
b100000 ,
1G
1F
0E
0D
#34000
1&
1+
1>
b0 K
b1 K
b10 K
b11 K
b100 K
b101 K
b110 K
b111 K
b1000 K
b100001000 3
b10111 /
b10100011011 L
b0 J
b0 K
b1 K
b111011 J
b10 K
b1101101 J
b11 K
b100 K
b101 K
b10001001 J
b110 K
b111 K
b1000 K
b1001 K
b100111101 H
1=
1;
19
18
0*
b11111 1
#34500
0&
0+
0>
b10011100 2
b100001 ,
0G
0F
1E
1D
0A
#35000
1&
1+
1>
b0 K
b1 K
b10 K
b11 K
b100 K
b101 K
b110 K
b111 K
b1000 K
b100111101 3
b11000 /
b10011010000 L
b0 J
b0 K
b111011 J
b1 K
b1101101 J
b10 K
b11 K
b100 K
b101 K
b110 K
b111 K
b1000 K
b1001 K
b100010100 H
0=
0:
08
1*
b100000 1
#35500
0&
0+
0>
b10001111 2
b100010 ,
1G
1F
0C
#36000
1&
1+
1>
b0 K
b1 K
b10 K
b11 K
b100 K
b101 K
b110 K
b111 K
b1000 K
b100010100 3
b11001 /
b10100100100 L
b0 J
b0 K
b1101101 J
b1 K
b10 K
b11 K
b10001001 J
b100 K
b101 K
b110 K
b111 K
b1000 K
b10001111 J
b1001 K
b101000101 H
1=
09
17
0*
b100001 1
#36500
0&
0+
0>
b11111000 2
b100011 ,
0G
0F
0E
1C
1B
1A
#37000
1&
1+
1>
b0 K
b1 K
b10 K
b11 K
b100 K
b101 K
b110 K
b111 K
b1000 K
b101000101 3
b11010 /
b10110101111 L
b0 J
b0 K
b110100 J
b1 K
b1100001 J
b10 K
b10001001 J
b11 K
b100 K
b101 K
b110 K
b10011100 J
b111 K
b1000 K
b1001 K
b101100101 H
18
1*
b100010 1
#37500
0&
0+
0>
b11101001 2
b100100 ,
1G
0C
#38000
1&
1+
1>
b0 K
b1 K
b10 K
b11 K
b100 K
b101 K
b110 K
b111 K
b1000 K
b101100101 3
b11011 /
b11001100100 L
b0 J
b0 K
b1100001 J
b1 K
b10001001 J
b10 K
b11 K
b100 K
b101 K
b10011100 J
b110 K
b111 K
b1000 K
b1001 K
b101111100 H
0=
1:
19
0*
b100011 1
#38500
0&
0+
0>
b1010000 2
b100101 ,
0G
0D
1C
0B
0@
#39000
1&
1+
1>
b0 K
b1 K
b10 K
b11 K
b100 K
b101 K
b110 K
b111 K
b1000 K
b101111100 3
b11100 /
b11001010011 L
b0 J
b0 K
b10001001 J
b1 K
b10 K
b11 K
b100 K
b10011100 J
b101 K
b110 K
b111 K
b1000 K
b1001 K
b101111001 H
1=
0;
1*
b100100 1
#39500
0&
0+
0>
b10100011 2
b100110 ,
1G
1F
0C
1B
0A
1@
#40000
1&
1+
1>
b0 K
b1 K
b10 K
b11 K
b100 K
b101 K
b110 K
b111 K
b1000 K
b101111001 3
b11101 /
b11001101101 L
b0 J
b0 K
b1 K
b10 K
b11 K
b10011100 J
b100 K
b101 K
b110 K
b111 K
b1000 K
b10100011 J
b1001 K
b110000101 H
1;
0:
09
08
07
16
0*
b100101 1
#40500
0&
0+
0>
b11111011 2
b100111 ,
1D
1C
1A
#41000
1&
1+
1>
b0 K
b1 K
b10 K
b11 K
b100 K
b101 K
b110 K
b111 K
b1000 K
b110000101 3
b11110 /
b11010101001 L
b0 J
b0 K
b1 K
b10 K
b10011100 J
b11 K
b100 K
b101 K
b110 K
b111 K
b10100011 J
b1000 K
b1001 K
b110001100 H
0=
1:
1*
b100110 1
#41500
0&
0+
0>
b10000011 2
b101000 ,
0D
0C
0B
0A
#42000
1&
1+
1>
b0 K
b1 K
b10 K
b11 K
b100 K
b101 K
b110 K
b111 K
b1000 K
b110001100 3
b11111 /
b11001010000 L
b0 J
b0 K
b1 K
b10011100 J
b10 K
b11 K
b100 K
b101 K
b110 K
b10100011 J
b111 K
b1000 K
b1001 K
b110000001 H
1=
0;
0:
0*
b100111 1
#42500
0&
0+
0>
b1101100 2
b101001 ,
0G
0F
1E
1D
1B
1A
0@
#43000
1&
1+
1>
b0 K
b1 K
b10 K
b11 K
b100 K
b101 K
b110 K
b111 K
b1000 K
b110000001 3
b100000 /
b10111101001 L
b0 J
b0 K
b10011100 J
b1 K
b10 K
b11 K
b100 K
b101 K
b10100011 J
b110 K
b111 K
b1000 K
b1001 K
b101110100 H
0=
1;
19
18
17
06
1*
b101000 1
#43500
0&
0+
0>
b10110000 2
b101010 ,
0E
0D
1C
0A
1@
#44000
1&
1+
1>
b0 K
b1 K
b10 K
b11 K
b100 K
b101 K
b110 K
b111 K
b1000 K
b101110100 3
b100001 /
b10111111101 L
b0 J
b0 K
b10001111 J
b1 K
b10 K
b11 K
b100 K
b10100011 J
b101 K
b110 K
b111 K
b1000 K
b1001 K
b101110111 H
1=
1<
0*
b101001 1
#44500
0&
0+
0>
b1100100 2
b101011 ,
1E
0C
1A
0@
#45000
1&
1+
1>
b0 K
b1 K
b10 K
b11 K
b100 K
b101 K
b110 K
b111 K
b1000 K
b101110111 3
b100010 /
b10111010010 L
b0 J
b0 K
b1 K
b10 K
b1010000 J
b11 K
b10100011 J
b100 K
b101 K
b110 K
b111 K
b1000 K
b1001 K
b101110001 H
0<
0;
1*
b101010 1
#45500
0&
0+
0>
b1010 2
b101100 ,
1F
0E
1D
0B
0A
#46000
1&
1+
1>
b0 K
b1 K
b10 K
b11 K
b100 K
b101 K
b110 K
b111 K
b1000 K
b101110001 3
b100011 /
b10011100100 L
b0 J
b0 K
b1 K
b1010000 J
b10 K
b11 K
b100 K
b10000011 J
b101 K
b110 K
b111 K
b1000 K
b1001 K
b100101111 H
1<
1;
1:
09
07
0*
b101011 1
#46500
0&
0+
0>
b11000101 2
b101101 ,
1G
0F
1E
0D
1A
1@
#47000
1&
1+
1>
b0 K
b1 K
b10 K
b11 K
b100 K
b101 K
b110 K
b111 K
b1000 K
b100101111 3
b100100 /
b10011000000 L
b0 J
b0 K
b1010000 J
b1 K
b10 K
b11 K
b10000011 J
b100 K
b101 K
b110 K
b111 K
b1000 K
b1001 K
b100101011 H
0;
1*
b101100 1
#47500
0&
0+
0>
b1011010 2
b101110 ,
0G
1F
0E
1D
1C
0@
#48000
1&
1+
1>
b0 K
b1 K
b10 K
b11 K
b100 K
b101 K
b110 K
b111 K
b1000 K
b100101011 3
b100101 /
b10011001010 L
b0 J
b0 K
b1 K
b10 K
b10000011 J
b11 K
b100 K
b101 K
b110 K
b111 K
b1000 K
b1001 K
b100101100 H
0=
0<
1;
0*
b101101 1
#48500
0&
0+
0>
b100 2
b101111 ,
0F
1E
0D
0C
0A
#49000
1&
1+
1>
b0 K
b1 K
b10 K
b11 K
b100 K
b101 K
b110 K
b111 K
b1000 K
b100101100 3
b100110 /
b10000101011 L
b0 J
b0 K
b1 K
b10 K
b1101100 J
b11 K
b100 K
b101 K
b110 K
b111 K
b1000 K
b1001 K
b11111110 H
1<
19
17
16
05
1*
b101110 1
#49500
0&
0+
0>
b1111001 2
b110000 ,
1G
0E
1D
1C
1B
1A
#50000
1&
1+
1>
b0 K
b1 K
b10 K
b11 K
b100 K
b101 K
b110 K
b111 K
b1000 K
b11111110 3
b100111 /
b1110101001 L
b0 J
b0 K
b1 K
b10 K
b11 K
b1100100 J
b100 K
b101 K
b110 K
b111 K
b1000 K
b1001 K
b11100101 H
1=
0<
0:
09
0*
b101111 1
#50500
0&
0+
0>
b101 2
b110001 ,
1E
0D
0C
0B
0A
#51000
1&
1+
1>
b0 K
b1 K
b10 K
b11 K
b100 K
b101 K
b110 K
b111 K
b1000 K
b11100101 3
b101000 /
b1100101011 L
b0 J
b0 K
b1 K
b10 K
b11 K
b1010 J
b100 K
b101 K
b1011010 J
b110 K
b111 K
b1000 K
b1001 K
b11001010 H
0=
1<
0;
1:
08
1*
b110000 1
#51500
0&
0+
0>
b10011000 2
b110010 ,
0G
0E
1D
1C
1@
#52000
1&
1+
1>
b0 K
b1 K
b10 K
b11 K
b100 K
b101 K
b110 K
b111 K
b1000 K
b11001010 3
b101001 /
b1101010111 L
b0 J
b0 K
b1 K
b10 K
b1010 J
b11 K
b100 K
b1011010 J
b101 K
b110 K
b111 K
b1000 K
b1001 K
b11010000 H
0<
0:
19
0*
b110001 1
#52500
0&
0+
0>
b111010 2
b110011 ,
1F
1B
0@
#53000
1&
1+
1>
b0 K
b1 K
b10 K
b11 K
b100 K
b101 K
b110 K
b111 K
b1000 K
b11010000 3
b101010 /
b1011100001 L
b0 J
b0 K
b1 K
b1010 J
b10 K
b11 K
b100 K
b101 K
b110 K
b111 K
b1000 K
b111010 J
b1001 K
b10011101 H
1=
1;
1:
07
1*
b110010 1
#53500
0&
0+
0>
b111011 2
b110100 ,
1G
#54000
1&
1+
1>
b0 K
b1 K
b10 K
b11 K
b100 K
b101 K
b110 K
b111 K
b1000 K
b10011101 3
b101011 /
b1010111000 L
b0 J
b0 K
b1010 J
b1 K
b10 K
b11 K
b100 K
b101 K
b110 K
b111 K
b111010 J
b1000 K
b111011 J
b1001 K
b10011001 H
0;
0*
b110011 1
#54500
0&
0+
0>
b11000011 2
b110101 ,
0D
0C
0B
1A
1@
#55000
1&
1+
1>
b0 K
b1 K
b10 K
b11 K
b100 K
b101 K
b110 K
b111 K
b1000 K
b10011001 3
b101100 /
b1101110001 L
b0 J
b0 K
b1 K
b1011010 J
b10 K
b11 K
b100 K
b101 K
b110 K
b111 K
b1000 K
b1001 K
b11010011 H
1<
0:
17
1*
b110100 1
#55500
0&
0+
0>
b101101 2
b110110 ,
0F
1E
1D
1B
0A
0@
#56000
1&
1+
1>
b0 K
b1 K
b10 K
b11 K
b100 K
b101 K
b110 K
b111 K
b1000 K
b11010011 3
b101101 /
b1011011001 L
b0 J
b0 K
b1 K
b100 J
b10 K
b11 K
b101 J
b100 K
b101 K
b111010 J
b110 K
b111011 J
b111 K
b1000 K
b1001 K
b10011101 H
0<
1;
1:
07
0*
b110101 1
#56500
0&
0+
0>
b10010110 2
b110111 ,
0G
1F
0D
1C
0B
1@
#57000
1&
1+
1>
b0 K
b1 K
b10 K
b11 K
b100 K
b101 K
b110 K
b111 K
b1000 K
b10011101 3
b101110 /
b1100010101 L
b0 J
b0 K
b100 J
b1 K
b10 K
b101 J
b11 K
b100 K
b111010 J
b101 K
b111011 J
b110 K
b111 K
b1000 K
b1001 K
b10100101 H
0:
09
18
1*
b110110 1
