2007/lcd_ctrl.v
module lcd_ctrl(clk, reset, datain, cmd, cmd_valid, dataout, output_valid, busy);
input             clk;
input             reset;
input   [7:0]     datain;
input   [2:0]     cmd;
input             cmd_valid;
output  reg [7:0] dataout;
output  reg       output_valid;
output  reg       busy;

reg  [7:0] image_buf [0:35];
reg  [7:0] out_play [0:8];
reg  [5:0] count_in;//count when datain -> image_buf
reg  [3:0] count_out;//count when out_play -> dataout
reg  [2:0] cmd_use;//the input cmd
reg [2:0] x ;
reg [2:0] y ;
reg [3:0] count;//count when image_buf -> out_play

integer i;

wire  [7:0] loc [8:0];//record the output location 
reg sub_one ;//check if there had substract 1

assign loc[0] =  x + (y<<2) + (y<<1) ;//2 2 14
assign loc[1] =  x + (y<<2) + (y<<1) +1;
assign loc[2] =  x + (y<<2) + (y<<1) +2;
assign loc[3] =  x + (y<<2) + (y<<1) +6 ;
assign loc[4] =  x + (y<<2) + (y<<1) +6 +1;
assign loc[5] =  x + (y<<2) + (y<<1) +6 +2;
assign loc[6] =  x + (y<<2) + (y<<1) +12 ;
assign loc[7] =  x + (y<<2) + (y<<1) +12 +1;
assign loc[8] =  x + (y<<2) + (y<<1) +12 +2;

always@(posedge reset or posedge clk)
begin
    /* reset the variable */
    if(reset)
    begin
        dataout <= 8'b0;
        output_valid <= 0;
        busy <= 0;
        count_in <= 0;
        count_out <= 0;
        cmd_use <= 0;
        for(i=0;i<36;i=i+1)
            image_buf[i] <= 0 ;
        for(i=0;i<9;i=i+1)
            out_play[i] <= 0 ;
        count <= 0;
        x  <= 0;
        y <= 0;
        sub_one <= 0;
    end

    else
    begin
        if(cmd_valid && !busy)//when read the cmd(not read in or read out anything)
        begin
            cmd_use <= cmd;
            busy <= 1;
            count_in <= 0;
            count_out <= 0;
            sub_one <= 0;
        end

        else
        begin
            /* control the cmd */
            case(cmd_use)
                3'b000://reflash
                begin
                    x <= x;
                    y <= y;
                end
                3'b001://load data
                begin
                    x <= 3'b010;
                    y <= 3'b010;
                end
                3'b010://shift right
                begin
                    if(x<3'b011 && sub_one==0)
                    begin
                        x <= x+1;
                        sub_one <= 1;
                    end
                    else
                        x <= x;
                    y <= y;
                end
                3'b011://shift left
                begin
                    if(x>3'b000 && sub_one==0)
                    begin
                        x <= x-1;
                        sub_one <= 1;
                    end
                    else
                        x <= x;
                    y <= y;
                end
                3'b100://shift up
                begin
                    if(y>3'b000 && sub_one==0)
                    begin
                        y <= y-1;
                        sub_one <= 1;
                    end
                    else
                        y <= y;
                    x <= x;

                end
                3'b101://shift down
                begin
                    if(y<3'b011 && sub_one ==0)
                    begin
                        y <= y +1;
                        sub_one <= 1;
                    end
                    else
                        y <= y;
                    x <= x;
                end
            endcase

            if(count != 9)
            begin
                count <= count + 1 ;
                out_play[count] <= image_buf[loc[count]];
            end

            else
            begin
                count <= 0;
                //x <= x;
                //y <= y ;
            end

            /* control the input and output */
            if(count_in == 6'b100100)//36//start to output
            begin
                output_valid <= 1;

                if(count_out == 4'b1001)//9//start the new round
                begin
                    busy <= 0;
                    output_valid <= 0;
                end
                else
                begin
                    count_out <= count_out +1 ;
                    dataout <= out_play[count_out] ;
                end
            end
            else
            begin
                count_in <= count_in+1;
                output_valid <= output_valid ;
                if(cmd_use==3'b001)
                    image_buf[count_in] <= datain;
                else
                    image_buf[count_in] <=image_buf[count_in];
            end

            cmd_use <= cmd_use;
        end
    end
end

endmodule

2007/testfixture.v
`timescale 1ns/10ps
`define CYCLE    100                        // Modify your clock period here
`define SDFFILE  "./LCD_CTRL.sdf"	    // Modify your sdf file name
`define IMAGE    "./image1.dat"             // Modify your test image file: image1.dat or image2.dat
`define CMD      "./cmd1.dat"               // Modify your test cmd file: cmd1.dat or cmd2.dat
`define EXPECT   "./out_golden1.dat"        // Modify your output golden file: out_golden1.dat or out_golden2.dat

module test;
parameter IMAGE_N_PAT = 36;         // 6x6 = 36 pixels
parameter CMD_N_PAT = 30;           // number of commands
parameter OUT_LENGTH = 270;         // output length = (3x3) * CMD_N_PAT
parameter t_reset = `CYCLE*2;

reg           clk;
reg           reset;
reg   [7:0]   datain;
reg   [2:0]   cmd;
reg           cmd_valid;
wire  [7:0]   dataout;
wire          output_valid;
wire          busy;

reg   [7:0]   image_mem [0:IMAGE_N_PAT-1];
reg   [2:0]   cmd_mem   [0:CMD_N_PAT-1];
reg   [7:0]   out_mem   [0:OUT_LENGTH-1];
reg   [7:0]   out_temp;

reg           stop;
integer       i, j, out_f, err, pattern_num;
reg           over;

   lcd_ctrl top(.clk(clk), .reset(reset), .datain(datain), 
                .cmd(cmd), .cmd_valid(cmd_valid), .dataout(dataout), 
                .output_valid(output_valid), .busy(busy));          
   


//initial $sdf_annotate(`SDFFILE, top);

initial	$readmemh (`IMAGE,  image_mem);
initial	$readmemh (`CMD,    cmd_mem);
initial	$readmemh (`EXPECT, out_mem);

initial begin
   clk         = 1'b0;
   reset       = 1'b0;
   cmd_valid   = 1'b0;
   stop        = 1'b0;  
   over        = 1'b0;
   pattern_num = 0;
   err         = 0;    
end

always begin #(`CYCLE/2) clk = ~clk; end

initial begin
$dumpfile("LCD_CTRL.vcd");
$dumpvars;
//$fsdbDumpfile("LCD_CTRL.fsdb");
//$fsdbDumpvars;

   out_f = $fopen("out.dat");
   if (out_f == 0) begin
        $display("Output file open error !");
        $finish;
   end
end


initial begin
   @(negedge clk)  reset = 1'b1;
   #t_reset        reset = 1'b0;
   
   @(negedge clk)    i=0;
   while (i <= CMD_N_PAT) begin               
      if(!busy) begin
        cmd = cmd_mem[i];
        cmd_valid = 1'b1;  
        
        if(cmd_mem[i] === 3'h1) begin    //cmd: Load data        
           for(j=0; j<=IMAGE_N_PAT; j=j+1)begin
              @(negedge clk) datain = image_mem[j];
                             cmd = 'hz; cmd_valid = 1'b0;
           end
           i = i+1;
        end
        else begin                      //cmd: other command
           @(negedge clk) datain='hz; cmd_valid = 1'b0; i = i+1;
        end       
      end 
      else begin
         datain='hz; cmd = 'hz;  cmd_valid = 0;
         @(negedge clk);
      end               
    end                                       
    stop = 1 ;      
end

always @(posedge clk)begin
   out_temp = out_mem[pattern_num];
   if(output_valid)begin
      $fdisplay(out_f,"%h", dataout);
      if(dataout !== out_temp) begin
         $display("ERROR at %d:output %h !=expect %h ",pattern_num, dataout, out_temp);
         err = err + 1 ;
      end
      pattern_num = pattern_num + 1;      
   end
   if(pattern_num === OUT_LENGTH)  over = 1'b1;
end


initial begin
      @(posedge stop)      
      if((over) || (pattern_num!='h0)) begin
         $display("---------------------------------------------\n");
         if (err == 0)  begin
            $display("All data have been generated successfully!\n");
            $display("-------------------PASS-------------------\n");
         end
         else 
            $display("There are %d errors!\n", err);
            $display("---------------------------------------------\n");
      end
      else begin
        $display("---------------------------------------------\n");
        $display("Error!!! There is no any data output ...!\n");
        $display("-------------------FAIL-------------------\n");
        $display("---------------------------------------------\n");
      end
      $finish;
end
   
endmodule

2007/LCD_CTRL.vcd
$date
	Thu Feb 24 02:09:13 2022
$end
$version
	ModelSim Version 10.1c
$end
$timescale
	10ps
$end
$scope module test $end
$var parameter 32 ! IMAGE_N_PAT $end
$var parameter 32 " CMD_N_PAT $end
$var parameter 32 # OUT_LENGTH $end
$var parameter 32 $ t_reset $end
$var reg 1 % clk $end
$var reg 1 & reset $end
$var reg 8 ' datain [7:0] $end
$var reg 3 ( cmd [2:0] $end
$var reg 1 ) cmd_valid $end
$var wire 1 * dataout [7] $end
$var wire 1 + dataout [6] $end
$var wire 1 , dataout [5] $end
$var wire 1 - dataout [4] $end
$var wire 1 . dataout [3] $end
$var wire 1 / dataout [2] $end
$var wire 1 0 dataout [1] $end
$var wire 1 1 dataout [0] $end
$var wire 1 2 output_valid $end
$var wire 1 3 busy $end
$var reg 8 4 out_temp [7:0] $end
$var reg 1 5 stop $end
$var integer 32 6 i $end
$var integer 32 7 j $end
$var integer 32 8 out_f $end
$var integer 32 9 err $end
$var integer 32 : pattern_num $end
$var reg 1 ; over $end
$scope module top $end
$var wire 1 < clk $end
$var wire 1 = reset $end
$var wire 1 > datain [7] $end
$var wire 1 ? datain [6] $end
$var wire 1 @ datain [5] $end
$var wire 1 A datain [4] $end
$var wire 1 B datain [3] $end
$var wire 1 C datain [2] $end
$var wire 1 D datain [1] $end
$var wire 1 E datain [0] $end
$var wire 1 F cmd [2] $end
$var wire 1 G cmd [1] $end
$var wire 1 H cmd [0] $end
$var wire 1 I cmd_valid $end
$var reg 8 J dataout [7:0] $end
$var reg 1 K output_valid $end
$var reg 1 L busy $end
$var reg 6 M count_in [5:0] $end
$var reg 4 N count_out [3:0] $end
$var reg 3 O cmd_use [2:0] $end
$var reg 3 P x [2:0] $end
$var reg 3 Q y [2:0] $end
$var reg 4 R count [3:0] $end
$var integer 32 S i $end
$var wire 1 T loc $end
$var reg 1 U sub_one $end
$upscope $end
$upscope $end
$enddefinitions $end
#0
$dumpvars
0%
0&
bx '
bx (
0)
bx 4
05
0;
bx J
xK
xL
bx M
bx N
bx O
bx P
bx Q
bx R
xU
b100100 !
b11110 "
b100001110 #
b11001000 $
bx 6
bx 7
b10 8
b0 9
b0 :
bx S
x1
x0
x/
x.
x-
x,
x+
x*
x2
x3
xT
0I
xH
xG
xF
xE
xD
xC
xB
xA
x@
x?
x>
0=
0<
$end
#5000
1%
1<
b1110 4
b0 R
#10000
0%
0<
1&
1=
b0 S
b1 S
b10 S
b11 S
b100 S
b101 S
b110 S
b111 S
b1000 S
b1001 S
b1010 S
b1011 S
b1100 S
b1101 S
b1110 S
b1111 S
b10000 S
b10001 S
b10010 S
b10011 S
b10100 S
b10101 S
b10110 S
b10111 S
b11000 S
b11001 S
b11010 S
b11011 S
b11100 S
b11101 S
b11110 S
b11111 S
b100000 S
b100001 S
b100010 S
b100011 S
b100100 S
b0 S
b1 S
b10 S
b11 S
b100 S
b101 S
b110 S
b111 S
b1000 S
b1001 S
b0 J
0K
0L
b0 M
b0 N
b0 O
b0 P
b0 Q
0U
02
03
0T
01
00
0/
0.
0-
0,
0+
0*
#15000
1%
1<
b0 S
b1 S
b10 S
b11 S
b100 S
b101 S
b110 S
b111 S
b1000 S
b1001 S
b1010 S
b1011 S
b1100 S
b1101 S
b1110 S
b1111 S
b10000 S
b10001 S
b10010 S
b10011 S
b10100 S
b10101 S
b10110 S
b10111 S
b11000 S
b11001 S
b11010 S
b11011 S
b11100 S
b11101 S
b11110 S
b11111 S
b100000 S
b100001 S
b100010 S
b100011 S
b100100 S
b0 S
b1 S
b10 S
b11 S
b100 S
b101 S
b110 S
b111 S
b1000 S
b1001 S
#20000
0%
0<
#25000
1%
1<
b0 S
b1 S
b10 S
b11 S
b100 S
b101 S
b110 S
b111 S
b1000 S
b1001 S
b1010 S
b1011 S
b1100 S
b1101 S
b1110 S
b1111 S
b10000 S
b10001 S
b10010 S
b10011 S
b10100 S
b10101 S
b10110 S
b10111 S
b11000 S
b11001 S
b11010 S
b11011 S
b11100 S
b11101 S
b11110 S
b11111 S
b100000 S
b100001 S
b100010 S
b100011 S
b100100 S
b0 S
b1 S
b10 S
b11 S
b100 S
b101 S
b110 S
b111 S
b1000 S
b1001 S
#30000
0&
0%
0=
0<
b0 6
b1 (
1)
b0 7
1H
0G
0F
1I
#35000
1%
1<
b1 O
1L
13
#40000
0%
0<
b0 '
bz (
0)
b1 7
zH
zG
zF
0E
0D
0C
0B
0A
0@
0?
0>
0I
#45000
1%
1<
b10 P
b10 Q
b1 R
b1 M
#50000
0%
0<
b1 '
b10 7
1E
#55000
1%
1<
b10 R
b10 M
#60000
0%
0<
b10 '
b11 7
0E
1D
#65000
1%
1<
b11 R
b11 M
#70000
0%
0<
b11 '
b100 7
1E
#75000
1%
1<
b100 R
b100 M
#80000
0%
0<
b100 '
b101 7
0E
0D
1C
#85000
1%
1<
b101 R
b101 M
#90000
0%
0<
b101 '
b110 7
1E
#95000
1%
1<
b110 R
b110 M
#100000
0%
0<
b110 '
b111 7
0E
1D
#105000
1%
1<
b111 R
b111 M
#110000
0%
0<
b111 '
b1000 7
1E
#115000
1%
1<
b1000 R
b1000 M
#120000
0%
0<
b1000 '
b1001 7
0E
0D
0C
1B
#125000
1%
1<
b1001 R
b1001 M
#130000
0%
0<
b1001 '
b1010 7
1E
#135000
1%
1<
b0 R
b1010 M
#140000
0%
0<
b1010 '
b1011 7
0E
1D
#145000
1%
1<
b1 R
b1011 M
#150000
0%
0<
b1011 '
b1100 7
1E
#155000
1%
1<
b10 R
b1100 M
#160000
0%
0<
b1100 '
b1101 7
0E
0D
1C
#165000
1%
1<
b11 R
b1101 M
#170000
0%
0<
b1101 '
b1110 7
1E
#175000
1%
1<
b100 R
b1110 M
#180000
0%
0<
b1110 '
b1111 7
0E
1D
#185000
1%
1<
b101 R
b1111 M
#190000
0%
0<
b1111 '
b10000 7
1E
#195000
1%
1<
b110 R
b10000 M
#200000
0%
0<
b10000 '
b10001 7
0E
0D
0C
0B
1A
#205000
1%
1<
b111 R
b10001 M
#210000
0%
0<
b10001 '
b10010 7
1E
#215000
1%
1<
b1000 R
b10010 M
#220000
0%
0<
b10010 '
b10011 7
0E
1D
#225000
1%
1<
b1001 R
b10011 M
#230000
0%
0<
b10011 '
b10100 7
1E
#235000
1%
1<
b0 R
b10100 M
#240000
0%
0<
b10100 '
b10101 7
0E
0D
1C
#245000
1%
1<
b1 R
b10101 M
#250000
0%
0<
b10101 '
b10110 7
1E
#255000
1%
1<
b10 R
b10110 M
#260000
0%
0<
b10110 '
b10111 7
0E
1D
#265000
1%
1<
b11 R
b10111 M
#270000
0%
0<
b10111 '
b11000 7
1E
#275000
1%
1<
b100 R
b11000 M
#280000
0%
0<
b11000 '
b11001 7
0E
0D
0C
1B
#285000
1%
1<
b101 R
b11001 M
#290000
0%
0<
b11001 '
b11010 7
1E
#295000
1%
1<
b110 R
b11010 M
#300000
0%
0<
b11010 '
b11011 7
0E
1D
#305000
1%
1<
b111 R
b11011 M
#310000
0%
0<
b11011 '
b11100 7
1E
#315000
1%
1<
b1000 R
b11100 M
#320000
0%
0<
b11100 '
b11101 7
0E
0D
1C
#325000
1%
1<
b1001 R
b11101 M
#330000
0%
0<
b11101 '
b11110 7
1E
#335000
1%
1<
b0 R
b11110 M
#340000
0%
0<
b11110 '
b11111 7
0E
1D
#345000
1%
1<
b1 R
b11111 M
#350000
0%
0<
b11111 '
b100000 7
1E
#355000
1%
1<
b10 R
b100000 M
#360000
0%
0<
b100000 '
b100001 7
0E
0D
0C
0B
0A
1@
#365000
1%
1<
b11 R
b100001 M
#370000
0%
0<
b100001 '
b100010 7
1E
#375000
1%
1<
b100 R
b100010 M
#380000
0%
0<
b100010 '
b100011 7
0E
1D
#385000
1%
1<
b101 R
b100011 M
#390000
0%
0<
b100011 '
b100100 7
1E
#395000
1%
1<
b110 R
b100100 M
#400000
0%
0<
bx '
b100101 7
b1 6
bz '
zE
zD
zC
zB
zA
z@
z?
z>
#405000
1%
1<
b111 R
1K
b1 N
b1110 J
12
10
1/
1.
#410000
0%
0<
#415000
1%
1<
b1 :
b1000 R
b10 N
b1111 J
11
#420000
0%
0<
#425000
1%
1<
b1111 4
b10 :
b1001 R
b11 N
b10000 J
01
00
0/
0.
1-
#430000
0%
0<
#435000
1%
1<
b10000 4
b11 :
b0 R
b100 N
b10100 J
1/
#440000
0%
0<
#445000
1%
1<
b10100 4
b100 :
b1 R
b101 N
b10101 J
11
#450000
0%
0<
#455000
1%
1<
b10101 4
b101 :
b10 R
b110 N
b10110 J
01
10
#460000
0%
0<
#465000
1%
1<
b10110 4
b110 :
b11 R
b111 N
b11010 J
0/
1.
#470000
0%
0<
#475000
1%
1<
b11010 4
b111 :
b100 R
b1000 N
b11011 J
11
#480000
0%
0<
#485000
1%
1<
b11011 4
b1000 :
b101 R
b1001 N
b11100 J
01
00
1/
#490000
0%
0<
#495000
1%
1<
b11100 4
b1001 :
b110 R
0L
0K
03
02
#500000
0%
0<
b10 (
1)
0H
1G
0F
1I
#505000
1%
1<
b1111 4
b10 O
1L
b0 M
b0 N
13
#510000
0%
0<
0)
b10 6
bz (
0I
zH
zG
zF
#515000
1%
1<
b11 P
1U
b111 R
b1 M
1T
#520000
0%
0<
#525000
1%
1<
b1000 R
b10 M
#530000
0%
0<
#535000
1%
1<
b1001 R
b11 M
#540000
0%
0<
#545000
1%
1<
b0 R
b100 M
#550000
0%
0<
#555000
1%
1<
b1 R
b101 M
#560000
0%
0<
#565000
1%
1<
b10 R
b110 M
#570000
0%
0<
#575000
1%
1<
b11 R
b111 M
#580000
0%
0<
#585000
1%
1<
b100 R
b1000 M
#590000
0%
0<
#595000
1%
1<
b101 R
b1001 M
#600000
0%
0<
#605000
1%
1<
b110 R
b1010 M
#610000
0%
0<
#615000
1%
1<
b111 R
b1011 M
#620000
0%
0<
#625000
1%
1<
b1000 R
b1100 M
#630000
0%
0<
#635000
1%
1<
b1001 R
b1101 M
#640000
0%
0<
#645000
1%
1<
b0 R
b1110 M
#650000
0%
0<
#655000
1%
1<
b1 R
b1111 M
#660000
0%
0<
#665000
1%
1<
b10 R
b10000 M
#670000
0%
0<
#675000
1%
1<
b11 R
b10001 M
#680000
0%
0<
#685000
1%
1<
b100 R
b10010 M
#690000
0%
0<
#695000
1%
1<
b101 R
b10011 M
#700000
0%
0<
#705000
1%
1<
b110 R
b10100 M
#710000
0%
0<
#715000
1%
1<
b111 R
b10101 M
#720000
0%
0<
#725000
1%
1<
b1000 R
b10110 M
#730000
0%
0<
#735000
1%
1<
b1001 R
b10111 M
#740000
0%
0<
#745000
1%
1<
b0 R
b11000 M
#750000
0%
0<
#755000
1%
1<
b1 R
b11001 M
#760000
0%
0<
#765000
1%
1<
b10 R
b11010 M
#770000
0%
0<
#775000
1%
1<
b11 R
b11011 M
#780000
0%
0<
#785000
1%
1<
b100 R
b11100 M
#790000
0%
0<
#795000
1%
1<
b101 R
b11101 M
#800000
0%
0<
#805000
1%
1<
b110 R
b11110 M
#810000
0%
0<
#815000
1%
1<
b111 R
b11111 M
#820000
0%
0<
#825000
1%
1<
b1000 R
b100000 M
#830000
0%
0<
#835000
1%
1<
b1001 R
b100001 M
#840000
0%
0<
#845000
1%
1<
b0 R
b100010 M
#850000
0%
0<
#855000
1%
1<
b1 R
b100011 M
#860000
0%
0<
#865000
1%
1<
b10 R
b100100 M
#870000
0%
0<
#875000
1%
1<
b11 R
1K
b1 N
b1111 J
12
11
10
0-
#880000
0%
0<
#885000
1%
1<
b1010 :
b100 R
b10 N
b10000 J
01
00
0/
0.
1-
#890000
0%
0<
#895000
1%
1<
b10000 4
b1011 :
b101 R
b11 N
b10001 J
11
#900000
0%
0<
#905000
1%
1<
b10001 4
b1100 :
b110 R
b100 N
b10101 J
1/
#910000
0%
0<
#915000
1%
1<
b10101 4
b1101 :
b111 R
b101 N
b10110 J
01
10
#920000
0%
0<
#925000
1%
1<
b10110 4
b1110 :
b1000 R
b110 N
b10111 J
11
#930000
0%
0<
#935000
1%
1<
b10111 4
b1111 :
b1001 R
b111 N
b11011 J
0/
1.
#940000
0%
0<
#945000
1%
1<
b11011 4
b10000 :
b0 R
b1000 N
b11100 J
01
00
1/
#950000
0%
0<
#955000
1%
1<
b11100 4
b10001 :
b1 R
b1001 N
b11101 J
11
#960000
0%
0<
#965000
1%
1<
b11101 4
b10010 :
b10 R
0L
0K
03
02
#970000
0%
0<
b101 (
1)
1H
0G
1F
1I
#975000
1%
1<
b10101 4
b101 O
1L
b0 M
b0 N
0U
13
#980000
0%
0<
0)
b11 6
bz (
0I
zH
zG
zF
#985000
1%
1<
b11 Q
1U
b11 R
b1 M
#990000
0%
0<
#995000
1%
1<
b100 R
b10 M
#1000000
0%
0<
#1005000
1%
1<
b101 R
b11 M
#1010000
0%
0<
#1015000
1%
1<
b110 R
b100 M
#1020000
0%
0<
#1025000
1%
1<
b111 R
b101 M
#1030000
0%
0<
#1035000
1%
1<
b1000 R
b110 M
#1040000
0%
0<
#1045000
1%
1<
b1001 R
b111 M
#1050000
0%
0<
#1055000
1%
1<
b0 R
b1000 M
#1060000
0%
0<
#1065000
1%
1<
b1 R
b1001 M
#1070000
0%
0<
#1075000
1%
1<
b10 R
b1010 M
#1080000
0%
0<
#1085000
1%
1<
b11 R
b1011 M
#1090000
0%
0<
#1095000
1%
1<
b100 R
b1100 M
#1100000
0%
0<
#1105000
1%
1<
b101 R
b1101 M
#1110000
0%
0<
#1115000
1%
1<
b110 R
b1110 M
#1120000
0%
0<
#1125000
1%
1<
b111 R
b1111 M
#1130000
0%
0<
#1135000
1%
1<
b1000 R
b10000 M
#1140000
0%
0<
#1145000
1%
1<
b1001 R
b10001 M
#1150000
0%
0<
#1155000
1%
1<
b0 R
b10010 M
#1160000
0%
0<
#1165000
1%
1<
b1 R
b10011 M
#1170000
0%
0<
#1175000
1%
1<
b10 R
b10100 M
#1180000
0%
0<
#1185000
1%
1<
b11 R
b10101 M
#1190000
0%
0<
#1195000
1%
1<
b100 R
b10110 M
#1200000
0%
0<
#1205000
1%
1<
b101 R
b10111 M
#1210000
0%
0<
#1215000
1%
1<
b110 R
b11000 M
#1220000
0%
0<
#1225000
1%
1<
b111 R
b11001 M
#1230000
0%
0<
#1235000
1%
1<
b1000 R
b11010 M
#1240000
0%
0<
#1245000
1%
1<
b1001 R
b11011 M
#1250000
0%
0<
#1255000
1%
1<
b0 R
b11100 M
#1260000
0%
0<
#1265000
1%
1<
b1 R
b11101 M
#1270000
0%
0<
#1275000
1%
1<
b10 R
b11110 M
#1280000
0%
0<
#1285000
1%
1<
b11 R
b11111 M
#1290000
0%
0<
#1295000
1%
1<
b100 R
b100000 M
#1300000
0%
0<
#1305000
1%
1<
b101 R
b100001 M
#1310000
0%
0<
#1315000
1%
1<
b110 R
b100010 M
#1320000
0%
0<
#1325000
1%
1<
b111 R
b100011 M
#1330000
0%
0<
#1335000
1%
1<
b1000 R
b100100 M
#1340000
0%
0<
#1345000
1%
1<
b1001 R
1K
b1 N
b10101 J
12
0.
#1350000
0%
0<
#1355000
1%
1<
b10011 :
b0 R
b10 N
b10110 J
01
10
#1360000
0%
0<
#1365000
1%
1<
b10110 4
b10100 :
b1 R
b11 N
b10111 J
11
#1370000
0%
0<
#1375000
1%
1<
b10111 4
b10101 :
b10 R
b100 N
b11011 J
0/
1.
#1380000
0%
0<
#1385000
1%
1<
b11011 4
b10110 :
b11 R
b101 N
b11100 J
01
00
1/
#1390000
0%
0<
#1395000
1%
1<
b11100 4
b10111 :
b100 R
b110 N
b11101 J
11
#1400000
0%
0<
#1405000
1%
1<
b11101 4
b11000 :
b101 R
b111 N
b100001 J
0/
0.
0-
1,
#1410000
0%
0<
#1415000
1%
1<
b100001 4
b11001 :
b110 R
b1000 N
b100010 J
01
10
#1420000
0%
0<
#1425000
1%
1<
b100010 4
b11010 :
b111 R
b1001 N
b100011 J
11
#1430000
0%
0<
#1435000
1%
1<
b100011 4
b11011 :
b1000 R
0L
0K
03
02
#1440000
0%
0<
b11 (
1)
1H
1G
0F
1I
#1445000
1%
1<
b10100 4
b11 O
1L
b0 M
b0 N
0U
13
#1450000
0%
0<
0)
b100 6
bz (
0I
zH
zG
zF
#1455000
1%
1<
b10 P
1U
b1001 R
b1 M
0T
#1460000
0%
0<
#1465000
1%
1<
b0 R
b10 M
#1470000
0%
0<
#1475000
1%
1<
b1 R
b11 M
#1480000
0%
0<
#1485000
1%
1<
b10 R
b100 M
#1490000
0%
0<
#1495000
1%
1<
b11 R
b101 M
#1500000
0%
0<
#1505000
1%
1<
b100 R
b110 M
#1510000
0%
0<
#1515000
1%
1<
b101 R
b111 M
#1520000
0%
0<
#1525000
1%
1<
b110 R
b1000 M
#1530000
0%
0<
#1535000
1%
1<
b111 R
b1001 M
#1540000
0%
0<
#1545000
1%
1<
b1000 R
b1010 M
#1550000
0%
0<
#1555000
1%
1<
b1001 R
b1011 M
#1560000
0%
0<
#1565000
1%
1<
b0 R
b1100 M
#1570000
0%
0<
#1575000
1%
1<
b1 R
b1101 M
#1580000
0%
0<
#1585000
1%
1<
b10 R
b1110 M
#1590000
0%
0<
#1595000
1%
1<
b11 R
b1111 M
#1600000
0%
0<
#1605000
1%
1<
b100 R
b10000 M
#1610000
0%
0<
#1615000
1%
1<
b101 R
b10001 M
#1620000
0%
0<
#1625000
1%
1<
b110 R
b10010 M
#1630000
0%
0<
#1635000
1%
1<
b111 R
b10011 M
#1640000
0%
0<
#1645000
1%
1<
b1000 R
b10100 M
#1650000
0%
0<
#1655000
1%
1<
b1001 R
b10101 M
#1660000
0%
0<
#1665000
1%
1<
b0 R
b10110 M
#1670000
0%
0<
#1675000
1%
1<
b1 R
b10111 M
#1680000
0%
0<
#1685000
1%
1<
b10 R
b11000 M
#1690000
0%
0<
#1695000
1%
1<
b11 R
b11001 M
#1700000
0%
0<
#1705000
1%
1<
b100 R
b11010 M
#1710000
0%
0<
#1715000
1%
1<
b101 R
b11011 M
#1720000
0%
0<
#1725000
1%
1<
b110 R
b11100 M
#1730000
0%
0<
#1735000
1%
1<
b111 R
b11101 M
#1740000
0%
0<
#1745000
1%
1<
b1000 R
b11110 M
#1750000
0%
0<
#1755000
1%
1<
b1001 R
b11111 M
#1760000
0%
0<
#1765000
1%
1<
b0 R
b100000 M
#1770000
0%
0<
#1775000
1%
1<
b1 R
b100001 M
#1780000
0%
0<
#1785000
1%
1<
b10 R
b100010 M
#1790000
0%
0<
#1795000
1%
1<
b11 R
b100011 M
#1800000
0%
0<
#1805000
1%
1<
b100 R
b100100 M
#1810000
0%
0<
#1815000
1%
1<
b101 R
1K
b1 N
b10100 J
12
01
00
1/
1-
0,
#1820000
0%
0<
#1825000
1%
1<
b11100 :
b110 R
b10 N
b10101 J
11
#1830000
0%
0<
#1835000
1%
1<
b10101 4
b11101 :
b111 R
b11 N
b10110 J
01
10
#1840000
0%
0<
#1845000
1%
1<
b10110 4
b11110 :
b1000 R
b100 N
b11010 J
0/
1.
#1850000
0%
0<
#1855000
1%
1<
b11010 4
b11111 :
b1001 R
b101 N
b11011 J
11
#1860000
0%
0<
#1865000
1%
1<
b11011 4
b100000 :
b0 R
b110 N
b11100 J
01
00
1/
#1870000
0%
0<
#1875000
1%
1<
b11100 4
b100001 :
b1 R
b111 N
b100000 J
0/
0.
0-
1,
#1880000
0%
0<
#1885000
1%
1<
b100000 4
b100010 :
b10 R
b1000 N
b100001 J
11
#1890000
0%
0<
#1895000
1%
1<
b100001 4
b100011 :
b11 R
b1001 N
b100010 J
01
10
#1900000
0%
0<
#1905000
1%
1<
b100010 4
b100100 :
b100 R
0L
0K
03
02
#1910000
0%
0<
b100 (
1)
0H
0G
1F
1I
#1915000
1%
1<
b1110 4
b100 O
1L
b0 M
b0 N
0U
13
#1920000
0%
0<
0)
b101 6
bz (
0I
zH
zG
zF
#1925000
1%
1<
b10 Q
1U
b101 R
b1 M
#1930000
0%
0<
#1935000
1%
1<
b110 R
b10 M
#1940000
0%
0<
#1945000
1%
1<
b111 R
b11 M
#1950000
0%
0<
#1955000
1%
1<
b1000 R
b100 M
#1960000
0%
0<
#1965000
1%
1<
b1001 R
b101 M
#1970000
0%
0<
#1975000
1%
1<
b0 R
b110 M
#1980000
0%
0<
#1985000
1%
1<
b1 R
b111 M
#1990000
0%
0<
#1995000
1%
1<
b10 R
b1000 M
#2000000
0%
0<
#2005000
1%
1<
b11 R
b1001 M
#2010000
0%
0<
#2015000
1%
1<
b100 R
b1010 M
#2020000
0%
0<
#2025000
1%
1<
b101 R
b1011 M
#2030000
0%
0<
#2035000
1%
1<
b110 R
b1100 M
#2040000
0%
0<
#2045000
1%
1<
b111 R
b1101 M
#2050000
0%
0<
#2055000
1%
1<
b1000 R
b1110 M
#2060000
0%
0<
#2065000
1%
1<
b1001 R
b1111 M
#2070000
0%
0<
#2075000
1%
1<
b0 R
b10000 M
#2080000
0%
0<
#2085000
1%
1<
b1 R
b10001 M
#2090000
0%
0<
#2095000
1%
1<
b10 R
b10010 M
#2100000
0%
0<
#2105000
1%
1<
b11 R
b10011 M
#2110000
0%
0<
#2115000
1%
1<
b100 R
b10100 M
#2120000
0%
0<
#2125000
1%
1<
b101 R
b10101 M
#2130000
0%
0<
#2135000
1%
1<
b110 R
b10110 M
#2140000
0%
0<
#2145000
1%
1<
b111 R
b10111 M
#2150000
0%
0<
#2155000
1%
1<
b1000 R
b11000 M
#2160000
0%
0<
#2165000
1%
1<
b1001 R
b11001 M
#2170000
0%
0<
#2175000
1%
1<
b0 R
b11010 M
#2180000
0%
0<
#2185000
1%
1<
b1 R
b11011 M
#2190000
0%
0<
#2195000
1%
1<
b10 R
b11100 M
#2200000
0%
0<
#2205000
1%
1<
b11 R
b11101 M
#2210000
0%
0<
#2215000
1%
1<
b100 R
b11110 M
#2220000
0%
0<
#2225000
1%
1<
b101 R
b11111 M
#2230000
0%
0<
#2235000
1%
1<
b110 R
b100000 M
#2240000
0%
0<
#2245000
1%
1<
b111 R
b100001 M
#2250000
0%
0<
#2255000
1%
1<
b1000 R
b100010 M
#2260000
0%
0<
#2265000
1%
1<
b1001 R
b100011 M
#2270000
0%
0<
#2275000
1%
1<
b0 R
b100100 M
#2280000
0%
0<
#2285000
1%
1<
b1 R
1K
b1 N
b1110 J
12
1/
1.
0,
#2290000
0%
0<
#2295000
1%
1<
b100101 :
b10 R
b10 N
b1111 J
11
#2300000
0%
0<
#2305000
1%
1<
b1111 4
b100110 :
b11 R
b11 N
b10000 J
01
00
0/
0.
1-
#2310000
0%
0<
#2315000
1%
1<
b10000 4
b100111 :
b100 R
b100 N
b10100 J
1/
#2320000
0%
0<
#2325000
1%
1<
b10100 4
b101000 :
b101 R
b101 N
b10101 J
11
#2330000
0%
0<
